ukpostcodes/__init__.py
ukpostcodes/ukpostcodes.py
ukpostcodes-1.0.0.dist-info/METADATA
ukpostcodes-1.0.0.dist-info/WHEEL
ukpostcodes-1.0.0.dist-info/top_level.txt
ukpostcodes-1.0.0.dist-info/RECORD
